docporter/__init__.py
docporter/cli.py
docporter/core.py
docporter-0.3.0.dist-info/METADATA
docporter-0.3.0.dist-info/WHEEL
docporter-0.3.0.dist-info/entry_points.txt
docporter-0.3.0.dist-info/top_level.txt
docporter-0.3.0.dist-info/RECORD
